smltk/__init__.py
smltk/data_analysis/__init__.py
smltk/data_analysis/data_analysis.py
smltk/data_processing/__init__.py
smltk/data_processing/data_processing.py
smltk/data_processing/ntk.py
smltk/feature_engineering/__init__.py
smltk/feature_engineering/indicator.py
smltk/modeling/__init__.py
smltk/modeling/classes_map.py
smltk/modeling/modeling.py
smltk/modeling/object_detection.py
smltk-3.0.0.dist-info/licenses/LICENSE
tests/__init__.py
tests/test_data_analysis.py
tests/test_data_processing.py
tests/test_indicator.py
tests/test_modeling.py
tests/test_ntk.py
tests/test_object_detection.py
tests/variables.py
smltk-3.0.0.dist-info/METADATA
smltk-3.0.0.dist-info/WHEEL
smltk-3.0.0.dist-info/top_level.txt
smltk-3.0.0.dist-info/RECORD
