Metadata-Version: 2.4
Name: smltk
Version: 3.0.0
Summary: Simple Machine Learning Tool Kit package
Home-page: https://smltk.readthedocs.io/
Author: Alessandra Bilardi
Author-email: Alessandra Bilardi <alessandra.bilardi@gmail.com>
License: MIT
Project-URL: Bug_Reports, https://github.com/bilardi/smltk/issues
Project-URL: Documentation, https://smltk.readthedocs.io/
Project-URL: Funding, https://donate.pypi.org
Project-URL: Source, https://github.com/bilardi/smltk
Classifier: Programming Language :: Python :: 3
Classifier: License :: OSI Approved :: MIT License
Classifier: Operating System :: OS Independent
Requires-Python: >=3.6
License-File: LICENSE
Requires-Dist: klib
Requires-Dist: matplotlib
Requires-Dist: mlxtend
Requires-Dist: numpy
Requires-Dist: pandas
Requires-Dist: scikit-learn
Requires-Dist: seaborn
Requires-Dist: simplemma
Requires-Dist: snowballstemmer
Requires-Dist: tokenizers
Provides-Extra: ntk
Requires-Dist: nltk; extra == "ntk"
Requires-Dist: wordcloud; extra == "ntk"
Provides-Extra: object-detection
Requires-Dist: torch; extra == "object-detection"
Provides-Extra: complete
Requires-Dist: nltk; extra == "complete"
Requires-Dist: torch; extra == "complete"
Requires-Dist: wordcloud; extra == "complete"
Dynamic: author
Dynamic: home-page
Dynamic: license-file
Dynamic: requires-python
